hass_nabucasa/__init__.py
hass_nabucasa/account_api.py
hass_nabucasa/account_link.py
hass_nabucasa/accounts_api.py
hass_nabucasa/acme.py
hass_nabucasa/alexa_api.py
hass_nabucasa/api.py
hass_nabucasa/client.py
hass_nabucasa/cloudhooks.py
hass_nabucasa/const.py
hass_nabucasa/exceptions.py
hass_nabucasa/files.py
hass_nabucasa/google_report_state.py
hass_nabucasa/ice_servers.py
hass_nabucasa/instance_api.py
hass_nabucasa/iot.py
hass_nabucasa/iot_base.py
hass_nabucasa/llm.py
hass_nabucasa/payments_api.py
hass_nabucasa/py.typed
hass_nabucasa/remote.py
hass_nabucasa/service_discovery.py
hass_nabucasa/utils.py
hass_nabucasa/voice.py
hass_nabucasa/voice_api.py
hass_nabucasa/voice_data.py
hass_nabucasa/auth/__init__.py
hass_nabucasa/auth/cognito.py
hass_nabucasa/events/__init__.py
hass_nabucasa/events/bus.py
hass_nabucasa/events/types.py
hass_nabucasa-1.7.0.dist-info/licenses/LICENSE
hass_nabucasa-1.7.0.dist-info/METADATA
hass_nabucasa-1.7.0.dist-info/WHEEL
hass_nabucasa-1.7.0.dist-info/top_level.txt
hass_nabucasa-1.7.0.dist-info/RECORD
