Metadata-Version: 2.4
Name: hass-nabucasa
Version: 1.7.0
Summary: Home Assistant cloud integration by Nabu Casa, Inc.
Author-email: "Nabu Casa, Inc." <opensource@nabucasa.com>
License-Expression: GPL-3.0-only
Platform: any
Classifier: Intended Audience :: End Users/Desktop
Classifier: Intended Audience :: Developers
Classifier: Operating System :: OS Independent
Classifier: Topic :: Internet :: Proxy Servers
Classifier: Topic :: Software Development :: Libraries :: Python Modules
Classifier: Development Status :: 5 - Production/Stable
Classifier: Programming Language :: Python :: 3.13
Requires-Python: >=3.13
License-File: LICENSE
Requires-Dist: acme==5.1.0
Requires-Dist: aiohttp>=3.6.1
Requires-Dist: async_timeout>=4
Requires-Dist: atomicwrites-homeassistant==1.4.1
Requires-Dist: attrs>=19.3
Requires-Dist: ciso8601>=2.3.0
Requires-Dist: cryptography>=42.0.0
Requires-Dist: grpcio<2,>=1.75.1
Requires-Dist: josepy<3,>=2
Requires-Dist: litellm<2,>=1.80.0
Requires-Dist: pycognito==2024.5.1
Requires-Dist: PyJWT>=2.8.0
Requires-Dist: snitun==0.45.1
Requires-Dist: voluptuous>=0.15
Requires-Dist: webrtc-models<1.0.0
Requires-Dist: yarl<2,>=1.20
Requires-Dist: sentence-stream<2,>=1.2.0
Provides-Extra: test
Requires-Dist: codespell==2.4.1; extra == "test"
Requires-Dist: freezegun==1.5.5; extra == "test"
Requires-Dist: mypy==1.18.2; extra == "test"
Requires-Dist: pre-commit==4.5.0; extra == "test"
Requires-Dist: pre-commit-hooks==6.0.0; extra == "test"
Requires-Dist: pylint==4.0.3; extra == "test"
Requires-Dist: pytest-aiohttp==1.1.0; extra == "test"
Requires-Dist: pytest-socket==0.7.0; extra == "test"
Requires-Dist: pytest-timeout==2.4.0; extra == "test"
Requires-Dist: pytest==9.0.1; extra == "test"
Requires-Dist: ruff==0.14.6; extra == "test"
Requires-Dist: types_atomicwrites==1.4.5.1; extra == "test"
Requires-Dist: types_pyOpenSSL==24.1.0.20240722; extra == "test"
Requires-Dist: xmltodict==1.0.2; extra == "test"
Requires-Dist: syrupy==5.0.0; extra == "test"
Requires-Dist: tomli==2.3.0; extra == "test"
Dynamic: license-file
